cernopendata_pages/__init__.py
cernopendata_pages/config.py
cernopendata_pages/version.py
cernopendata_pages/views.py
cernopendata_pages/static/img/default.png
cernopendata_pages/static/img/resources/VMs.jpg
cernopendata_pages/static/img/resources/learning.jpg
cernopendata_pages/static/img/visualisation/event.png
cernopendata_pages/static/img/visualisation/histogram.png
cernopendata_pages/templates/cernopendata_pages/base.html
cernopendata_pages/templates/cernopendata_pages/index.html
cernopendata_pages-1.0.0.dist-info/top_level.txt
cernopendata_pages-1.0.0.dist-info/entry_points.txt
cernopendata_pages-1.0.0.dist-info/METADATA
cernopendata_pages-1.0.0.dist-info/DESCRIPTION.rst
cernopendata_pages-1.0.0.dist-info/metadata.json
cernopendata_pages-1.0.0.dist-info/WHEEL
cernopendata_pages-1.0.0.dist-info/RECORD
